{
	"configurations" : 
	[
		{
			"directories" : 
			[
				{
					"build" : ".",
					"childIndexes" : 
					[
						1
					],
					"jsonFile" : "directory-.-Debug-f5ebdc15457944623624.json",
					"minimumCMakeVersion" : 
					{
						"string" : "3.5"
					},
					"projectIndex" : 0,
					"source" : "."
				},
				{
					"build" : "src",
					"jsonFile" : "directory-src-Debug-b6cf2213fc5053b67c22.json",
					"minimumCMakeVersion" : 
					{
						"string" : "3.5"
					},
					"parentIndex" : 0,
					"projectIndex" : 1,
					"source" : "src",
					"targetIndexes" : 
					[
						0,
						1,
						2,
						3,
						4,
						5,
						6,
						7,
						8,
						9,
						10
					]
				}
			],
			"name" : "Debug",
			"projects" : 
			[
				{
					"childIndexes" : 
					[
						1
					],
					"directoryIndexes" : 
					[
						0
					],
					"name" : "ch6"
				},
				{
					"directoryIndexes" : 
					[
						1
					],
					"name" : "chapter6",
					"parentIndex" : 0,
					"targetIndexes" : 
					[
						0,
						1,
						2,
						3,
						4,
						5,
						6,
						7,
						8,
						9,
						10
					]
				}
			],
			"targets" : 
			[
				{
					"directoryIndex" : 1,
					"id" : "date::@145eef247bfb46b6828c",
					"jsonFile" : "target-date-Debug-a8316bc672e0f7bec276.json",
					"name" : "date",
					"projectIndex" : 1
				},
				{
					"directoryIndex" : 1,
					"id" : "ex6_18::@145eef247bfb46b6828c",
					"jsonFile" : "target-ex6_18-Debug-a7e2ee9640f82f1c9b74.json",
					"name" : "ex6_18",
					"projectIndex" : 1
				},
				{
					"directoryIndex" : 1,
					"id" : "ex8_1::@145eef247bfb46b6828c",
					"jsonFile" : "target-ex8_1-Debug-9576ffd6f54ed1553672.json",
					"name" : "ex8_1",
					"projectIndex" : 1
				},
				{
					"directoryIndex" : 1,
					"id" : "ex8_15::@145eef247bfb46b6828c",
					"jsonFile" : "target-ex8_15-Debug-9891c1fe3154089591af.json",
					"name" : "ex8_15",
					"projectIndex" : 1
				},
				{
					"directoryIndex" : 1,
					"id" : "ex8_16::@145eef247bfb46b6828c",
					"jsonFile" : "target-ex8_16-Debug-be5f38f46178532494c1.json",
					"name" : "ex8_16",
					"projectIndex" : 1
				},
				{
					"directoryIndex" : 1,
					"id" : "ex8_19::@145eef247bfb46b6828c",
					"jsonFile" : "target-ex8_19-Debug-87fb0a37d25690f4fbb2.json",
					"name" : "ex8_19",
					"projectIndex" : 1
				},
				{
					"directoryIndex" : 1,
					"id" : "ex8_34::@145eef247bfb46b6828c",
					"jsonFile" : "target-ex8_34-Debug-18096f143ca197f0c894.json",
					"name" : "ex8_34",
					"projectIndex" : 1
				},
				{
					"directoryIndex" : 1,
					"id" : "ex8_37::@145eef247bfb46b6828c",
					"jsonFile" : "target-ex8_37-Debug-4c8f4bb9c7a6fdc579fb.json",
					"name" : "ex8_37",
					"projectIndex" : 1
				},
				{
					"directoryIndex" : 1,
					"id" : "ex8_38::@145eef247bfb46b6828c",
					"jsonFile" : "target-ex8_38-Debug-8514c9e5efd456cb425b.json",
					"name" : "ex8_38",
					"projectIndex" : 1
				},
				{
					"directoryIndex" : 1,
					"id" : "p254::@145eef247bfb46b6828c",
					"jsonFile" : "target-p254-Debug-629ce8a179a8800b71f0.json",
					"name" : "p254",
					"projectIndex" : 1
				},
				{
					"directoryIndex" : 1,
					"id" : "p383::@145eef247bfb46b6828c",
					"jsonFile" : "target-p383-Debug-79baeb804f21bfdd229b.json",
					"name" : "p383",
					"projectIndex" : 1
				}
			]
		}
	],
	"kind" : "codemodel",
	"paths" : 
	{
		"build" : "/home/iaa/Desktop/gitStore/Win10hdd/C_language/Chapter6/debugUnix",
		"source" : "/home/iaa/Desktop/gitStore/Win10hdd/C_language/Chapter6"
	},
	"version" : 
	{
		"major" : 2,
		"minor" : 6
	}
}
