{
	"configurations" : 
	[
		{
			"directories" : 
			[
				{
					"build" : ".",
					"childIndexes" : 
					[
						1
					],
					"jsonFile" : "directory-.-Debug-f5ebdc15457944623624.json",
					"minimumCMakeVersion" : 
					{
						"string" : "3.5"
					},
					"projectIndex" : 0,
					"source" : "."
				},
				{
					"build" : "src",
					"jsonFile" : "directory-src-Debug-b6cf2213fc5053b67c22.json",
					"minimumCMakeVersion" : 
					{
						"string" : "3.5"
					},
					"parentIndex" : 0,
					"projectIndex" : 1,
					"source" : "src",
					"targetIndexes" : 
					[
						0,
						1,
						2,
						3,
						4,
						5
					]
				}
			],
			"name" : "Debug",
			"projects" : 
			[
				{
					"childIndexes" : 
					[
						1
					],
					"directoryIndexes" : 
					[
						0
					],
					"name" : "ch5samples"
				},
				{
					"directoryIndexes" : 
					[
						1
					],
					"name" : "chapter5",
					"parentIndex" : 0,
					"targetIndexes" : 
					[
						0,
						1,
						2,
						3,
						4,
						5
					]
				}
			],
			"targets" : 
			[
				{
					"directoryIndex" : 1,
					"id" : "crebs::@145eef247bfb46b6828c",
					"jsonFile" : "target-crebs-Debug-a997cad8262244e15173.json",
					"name" : "crebs",
					"projectIndex" : 1
				},
				{
					"directoryIndex" : 1,
					"id" : "ex5_17::@145eef247bfb46b6828c",
					"jsonFile" : "target-ex5_17-Debug-50872eef39fcbefeb5a5.json",
					"name" : "ex5_17",
					"projectIndex" : 1
				},
				{
					"directoryIndex" : 1,
					"id" : "ex5_23::@145eef247bfb46b6828c",
					"jsonFile" : "target-ex5_23-Debug-3ed903ce080a563a5017.json",
					"name" : "ex5_23",
					"projectIndex" : 1
				},
				{
					"directoryIndex" : 1,
					"id" : "ex5_26::@145eef247bfb46b6828c",
					"jsonFile" : "target-ex5_26-Debug-fcd4abc1d6f9895565a7.json",
					"name" : "ex5_26",
					"projectIndex" : 1
				},
				{
					"directoryIndex" : 1,
					"id" : "ex5_28::@145eef247bfb46b6828c",
					"jsonFile" : "target-ex5_28-Debug-d62922756b7d17f0a86c.json",
					"name" : "ex5_28",
					"projectIndex" : 1
				},
				{
					"directoryIndex" : 1,
					"id" : "multiCrebs::@145eef247bfb46b6828c",
					"jsonFile" : "target-multiCrebs-Debug-3aed6f1fad14b7288c37.json",
					"name" : "multiCrebs",
					"projectIndex" : 1
				}
			]
		}
	],
	"kind" : "codemodel",
	"paths" : 
	{
		"build" : "/home/iaa/Desktop/gitStore/Win10hdd/C_language/chapter5/debugUnix",
		"source" : "/home/iaa/Desktop/gitStore/Win10hdd/C_language/chapter5"
	},
	"version" : 
	{
		"major" : 2,
		"minor" : 6
	}
}
